README
setup.py
cymru/__init__.py
cymru/bogon/__init__.py
cymru/bogon/dns.py
cymru/core/__init__.py
cymru/core/cache.py
cymru/core/dns.py
cymru/core/whois.py
cymru/ip2asn/__init__.py
cymru/ip2asn/dns.py
cymru/ip2asn/whois.py
cymru/mhr/__init__.py
cymru/mhr/dns.py
cymru/mhr/whois.py
cymru_services.egg-info/PKG-INFO
cymru_services.egg-info/SOURCES.txt
cymru_services.egg-info/dependency_links.txt
cymru_services.egg-info/requires.txt
cymru_services.egg-info/top_level.txt