Metadata-Version: 1.1
Name: cymru-services
Version: 1.4
Summary: Python API for the Cymru Services
Home-page: http://packages.python.org/cymru-services/
Author: Loic Jaquemet
Author-email: loic.jaquemet+python@gmail.com
License: GPL
Download-URL: http://github.com/trolldbois/python-cymru-services/tree/master
Keywords: ASN,MHR,PEER,IP,BOGON,cymru,python2,python3
Platform: UNKNOWN
Classifier: Topic :: System :: Networking
Classifier: Environment :: Console
Classifier: Intended Audience :: Developers
Classifier: License :: OSI Approved :: GNU General Public License (GPL)
Classifier: Programming Language :: Python
Classifier: Development Status :: 5 - Production/Stable
